ilo/__init__.py
ilo/ilo.py
ilo-0.0.58.dist-info/licenses/LICENSE
ilo-0.0.58.dist-info/METADATA
ilo-0.0.58.dist-info/WHEEL
ilo-0.0.58.dist-info/top_level.txt
ilo-0.0.58.dist-info/RECORD
