Metadata-Version: 2.4
Name: ilo
Version: 0.0.58
Summary: Control ilo robot using python command.
Author-email: "intuition RT (SLB)" <contact@ilorobot.com>
Maintainer-email: "intuition RT (SLB)" <contact@ilorobot.com>
License-Expression: MIT
Project-URL: Homepage, https://ilorobot.com
Project-URL: Documentation, https://ilorobot.com
Keywords: python,education,robot,ilo
Classifier: Development Status :: 4 - Beta
Classifier: Intended Audience :: Developers
Classifier: Intended Audience :: Education
Classifier: Natural Language :: English
Classifier: Programming Language :: Python :: 3
Classifier: Programming Language :: Python :: 3.8
Classifier: Programming Language :: Python :: 3.9
Classifier: Programming Language :: Python :: 3.10
Classifier: Programming Language :: Python :: 3.11
Classifier: Programming Language :: Python :: 3.12
Classifier: Programming Language :: Python :: 3.13
Classifier: Operating System :: MacOS :: MacOS X
Classifier: Operating System :: Microsoft :: Windows
Classifier: Operating System :: OS Independent
Classifier: Topic :: Education
Requires-Python: >=3.8
License-File: LICENSE
Requires-Dist: pyserial<4.0,>=3.4
Requires-Dist: psutil>=7.0.0
Requires-Dist: websocket-client<1.9.0,>=1.0.0
Requires-Dist: bleak<0.23.0,>=0.22.0
Requires-Dist: prettytable<3.12.0,>=2.0.0
Requires-Dist: keyboard_crossplatform<1.0.0,>=0.1.0
Requires-Dist: requests<2.33.0,>=2.25.0
Requires-Dist: keyboard>=0.13.5
Requires-Dist: packaging>=24.2
Requires-Dist: numpy<2.0.0,>=1.20.0; python_version < "3.13"
Requires-Dist: matplotlib<3.8.0,>=3.3.0; python_version < "3.13"
Requires-Dist: numpy>=2.1; python_version >= "3.13"
Requires-Dist: matplotlib>=3.10; python_version >= "3.13"
Provides-Extra: extras
Requires-Dist: pyperclip<2.0.0,>=1.8.0; extra == "extras"
Dynamic: license-file
